chandas/__init__.py
chandas/syllabize.py
chandas/chandas_relation/__init__.py
chandas/chandas_relation/ardhasama.py
chandas/svat/__init__.py
chandas/svat/data/__init__.py
chandas/svat/data/curated.py
chandas/svat/data/dhaval_mishra.py
chandas/svat/data/dhaval_vrttaratnakara.py
chandas/svat/data/ganesh.py
chandas/svat/data/metrical_data.py
chandas/svat/identify/__init__.py
chandas/svat/identify/identifier.py
chandas/svat/read/__init__.py
chandas/svat/read/filters.py
chandas/svat/read/read.py
chandas/svat/read/split_gretil.py
chandas-0.0.10.dist-info/LICENSE.txt
chandas-0.0.10.dist-info/METADATA
chandas-0.0.10.dist-info/WHEEL
chandas-0.0.10.dist-info/top_level.txt
chandas-0.0.10.dist-info/RECORD
