Metadata-Version: 2.1
Name: chandas
Version: 0.0.10
Summary: Metrical analysis tools for indic languages in general, and sanskrit in particular
Home-page: https://github.com/sanskrit-coders/chandas
Author: Sanskrit programmers
Author-email: sanskrit-programmers@googlegroups.com
License: MIT
Keywords: indic metre meter hindi sanskrit samskritam kannada devanagari tamil malayalam telugu gurumukhi gujarati bengali oriya) SLP1 WX
Platform: UNKNOWN
Classifier: Development Status :: 5 - Production/Stable
Classifier: Intended Audience :: Education
Classifier: Intended Audience :: Science/Research
Classifier: Intended Audience :: Developers
Classifier: Natural Language :: Hindi
Classifier: Natural Language :: Tamil
Classifier: Natural Language :: Bengali
Classifier: Natural Language :: Panjabi
Classifier: Natural Language :: Marathi
Classifier: Topic :: Text Processing :: Linguistic
Classifier: License :: OSI Approved :: MIT License
Classifier: Programming Language :: Python :: 3
Classifier: Programming Language :: Python :: 3.6
Classifier: Programming Language :: Python :: 3.7
License-File: LICENSE.txt
Requires-Dist: PyICU
Requires-Dist: unicodecsv
Requires-Dist: indic-transliteration
Provides-Extra: test
Requires-Dist: pytest; extra == "test"
